lib/linuxdoc/__init__.py
lib/linuxdoc/__pkginfo__.py
lib/linuxdoc/autodoc.py
lib/linuxdoc/cdomain.py
lib/linuxdoc/cdomainv2.py
lib/linuxdoc/cdomainv3.py
lib/linuxdoc/compat.py
lib/linuxdoc/deprecated.py
lib/linuxdoc/grepdoc.py
lib/linuxdoc/kernel_doc.py
lib/linuxdoc/kernel_include.py
lib/linuxdoc/kfigure.py
lib/linuxdoc/lint.py
lib/linuxdoc/manKernelDoc.py
lib/linuxdoc/rest.py
lib/linuxdoc/rstFlatTable.py
lib/linuxdoc/rstKernelDoc.py
lib/tests/__init__.py
linuxdoc/__init__.py
linuxdoc/__pkginfo__.py
linuxdoc/autodoc.py
linuxdoc/cdomain.py
linuxdoc/cdomainv2.py
linuxdoc/cdomainv3.py
linuxdoc/compat.py
linuxdoc/deprecated.py
linuxdoc/grepdoc.py
linuxdoc/kernel_doc.py
linuxdoc/kernel_include.py
linuxdoc/kfigure.py
linuxdoc/lint.py
linuxdoc/manKernelDoc.py
linuxdoc/rest.py
linuxdoc/rstFlatTable.py
linuxdoc/rstKernelDoc.py
tests/__init__.py
linuxdoc-20230827.dist-info/LICENSE
linuxdoc-20230827.dist-info/METADATA
linuxdoc-20230827.dist-info/WHEEL
linuxdoc-20230827.dist-info/entry_points.txt
linuxdoc-20230827.dist-info/top_level.txt
linuxdoc-20230827.dist-info/RECORD
