Metadata-Version: 2.1
Name: linuxdoc
Version: 20230827
Summary: Sphinx-doc extensions & tools to extract documentation from C/C++ source file comments.
Home-page: https://github.com/return42/linuxdoc
Author: Markus Heiser
Author-email: markus.heiser@darmarIT.de
License: AGPLv3+
Project-URL: Documentation, https://return42.github.io/linuxdoc
Project-URL: Code, https://github.com/return42/linuxdoc
Project-URL: Issue tracker, https://github.com/return42/linuxdoc/issues
Project-URL: Changelog, https://github.com/return42/linuxdoc/blob/master/CHANGELOG
Keywords: sphinx extension doc source code comments kernel-doc linux
Classifier: Development Status :: 5 - Production/Stable
Classifier: Intended Audience :: Developers
Classifier: Intended Audience :: Other Audience
Classifier: License :: OSI Approved :: GNU Affero General Public License v3 or later (AGPLv3+)
Classifier: Operating System :: OS Independent
Classifier: Programming Language :: Python
Classifier: Programming Language :: Python :: 3
Classifier: Topic :: Utilities
Classifier: Topic :: Software Development :: Documentation
Classifier: Topic :: Software Development :: Libraries
Classifier: Topic :: Text Processing
License-File: LICENSE
Requires-Dist: fspath
Requires-Dist: setuptools
Requires-Dist: docutils
Requires-Dist: sphinx
